__init__.py
saplangchainproxy/__init__.py
saplangchainproxy/sapwrapper.py
saplangchainproxy/chat/__init__.py
saplangchainproxy/chat/openai.py
saplangchainproxy/embeddings/__init__.py
saplangchainproxy/embeddings/openai.py
saplangchainproxy/llm/__init__.py
saplangchainproxy/llm/openai.py
saplangchainproxy/tests/__init__.py
saplangchainproxy/tests/test_proxy.py
saplangchainproxy/tests/test_streaming.py
sapapj_langchain_proxy-0.0.2.dist-info/LICENSE
sapapj_langchain_proxy-0.0.2.dist-info/METADATA
sapapj_langchain_proxy-0.0.2.dist-info/WHEEL
sapapj_langchain_proxy-0.0.2.dist-info/entry_points.txt
sapapj_langchain_proxy-0.0.2.dist-info/top_level.txt
sapapj_langchain_proxy-0.0.2.dist-info/RECORD
