Metadata-Version: 2.1
Name: sapapj-langchain-proxy
Version: 0.0.2
Summary: Connect langchain to SAP's AI proxy.
Author-email: Skye0402 <albrechg@yahoo.com>
License: MIT License
Project-URL: Homepage, https://github.com/skye0402/saplangchain-proxy
Keywords: langchain,sap,proxy
Classifier: License :: OSI Approved :: MIT License
Classifier: Programming Language :: Python
Classifier: Programming Language :: Python :: 3
Requires-Python: >=3.10
License-File: LICENSE
Requires-Dist: oauthlib >=3.2.2
Requires-Dist: requests-oauthlib >=1.3.1
Requires-Dist: tomli ; python_version < "3.11"
Provides-Extra: dev
Requires-Dist: black ; extra == 'dev'
Requires-Dist: bumpver ; extra == 'dev'
Requires-Dist: isort ; extra == 'dev'
Requires-Dist: pip-tools ; extra == 'dev'
Requires-Dist: pytest ; extra == 'dev'
